tg_to_obj/__init__.py
tg_to_obj/helper.py
tg_to_obj-1.0.0.dist-info/LICENSE
tg_to_obj-1.0.0.dist-info/METADATA
tg_to_obj-1.0.0.dist-info/WHEEL
tg_to_obj-1.0.0.dist-info/top_level.txt
tg_to_obj-1.0.0.dist-info/RECORD
